boinc_client/__init__.py
boinc_client/boinc_client.py
boinc_client/clients/__init__.py
boinc_client/clients/rpc_client.py
boinc_client/messages.py
boinc_client/models/__init__.py
boinc_client/models/cc_status.py
boinc_client/models/client_state.py
boinc_client/models/client_update.py
boinc_client/models/client_version.py
boinc_client/models/disk_stats.py
boinc_client/models/file_transfer.py
boinc_client/models/generic_response.py
boinc_client/models/global_preference_override.py
boinc_client/models/global_preferences.py
boinc_client/models/helpers.py
boinc_client/models/host_info.py
boinc_client/models/message_count.py
boinc_client/models/messages.py
boinc_client/models/network_transfers.py
boinc_client/models/old_results.py
boinc_client/models/project_attach.py
boinc_client/models/project_status.py
boinc_client/models/projects.py
boinc_client/models/projects_stats.py
boinc_client/models/proxy_settings.py
boinc_client/models/public_notice.py
boinc_client/models/result.py
boinc_client/models/screensaver_tasks.py
boinc_client/models/simple_gui_info.py
boinc_client/modes.py
boinc_client/network.py
boinc_client/preferences.py
boinc_client/projects.py
boinc_client/results.py
boinc_client/stats.py
boinc_client/status.py
boinc_client/versions.py
boinc_client-1.12.1.dist-info/WHEEL
boinc_client-1.12.1.dist-info/LICENSE.md
boinc_client-1.12.1.dist-info/METADATA
boinc_client-1.12.1.dist-info/RECORD
