Metadata-Version: 2.1
Name: boinc-client
Version: 1.12.1
Summary: Python API for interacting with a BOINC client via RPC
Author: Lewis England
Author-email: lewis2004@hotmail.com
Requires-Python: >=3.9,<4.0
Classifier: Programming Language :: Python :: 3
Classifier: Programming Language :: Python :: 3.9
Classifier: Programming Language :: Python :: 3.10
Classifier: Programming Language :: Python :: 3.11
Requires-Dist: lxml (>=4.9.2,<6.0.0)
Requires-Dist: marshmallow (>=3.19.0,<4.0.0)
Requires-Dist: xmltodict (>=0.13.0,<0.14.0)
Project-URL: homepage, https://github.com/SplinterHead/boinc-client
Project-URL: issues, https://github.com/SplinterHead/boinc-client/issues
